em_pyquil/__init__.py
em_pyquil-1.0.2.dist-info/LICENSE
em_pyquil-1.0.2.dist-info/METADATA
em_pyquil-1.0.2.dist-info/WHEEL
em_pyquil-1.0.2.dist-info/top_level.txt
em_pyquil-1.0.2.dist-info/RECORD
