Metadata-Version: 2.1
Name: em-pyquil
Version: 1.0.2
Summary: A Python library implementing error mitigation on pyquil programs.
Home-page: https://github.com/gate42qc/em-pyquil.git
Author: Gate42 Quantum Computing Lab
Author-email: team@gate42.org
License: MIT
Keywords: quantum quil programming pyquil error mitigation
Platform: UNKNOWN
Classifier: Development Status :: 5 - Production/Stable
Classifier: Intended Audience :: Science/Research
Classifier: License :: OSI Approved :: MIT License
Classifier: Programming Language :: Python :: 3
Classifier: Operating System :: OS Independent
Requires-Python: >=3.6
Requires-Dist: numpy
Requires-Dist: pyquil (>=2.10.0)
